{"name": "Uttar Pradesh", "slug": "uttar-pradesh", "type": "State", "center": [26.54, 80.159], "totalAccidents": 47889, "fatalAccidents": 10535, "highRiskDistricts": 16, "severityIndex": 9.8, "districts": ["Lucknow", "Kanpur Nagar", "Agra", "Varanasi", "Prayagraj", "Ghaziabad", "Meerut", "Noida"], "hotspots": [{"id": "uttar-pradesh-h1", "location": "Agra Bus Stand Road", "district": "Agra", "lat": 26.7405, "lng": 81.2582, "accidents": 431, "fatalities": 122, "majorCause": "Wrong-Side Driving", "vehicleType": "Bus", "roadType": "National Highway", "riskLevel": "Critical", "safetyTip": "Always follow lane discipline; wrong-side driving causes head-on collisions.", "yearly": {"2019": 72, "2020": 47, "2021": 56, "2022": 68, "2023": 76, "2024": 67}, "severity": "Minor"}, {"id": "uttar-pradesh-h2", "location": "Varanasi Flyover", "district": "Varanasi", "lat": 29.4122, "lng": 77.8389, "accidents": 243, "fatalities": 46, "majorCause": "Drunk Driving", "vehicleType": "Auto", "roadType": "State Highway", "riskLevel": "High", "safetyTip": "Never drive under the influence. Use a designated driver or cab service.", "yearly": {"2019": 52, "2020": 36, "2021": 31, "2022": 39, "2023": 39, "2024": 53}, "severity": "Minor"}, {"id": "uttar-pradesh-h3", "location": "Agra Toll Plaza", "district": "Agra", "lat": 28.1335, "lng": 77.7572, "accidents": 400, "fatalities": 96, "majorCause": "Vehicle Overloading", "vehicleType": "Bike", "roadType": "City Road", "riskLevel": "Critical", "safetyTip": "Avoid overloading \u2014 it destabilizes vehicles and increases braking distance.", "yearly": {"2019": 92, "2020": 50, "2021": 46, "2022": 76, "2023": 43, "2024": 47}, "severity": "Minor"}, {"id": "uttar-pradesh-h4", "location": "Prayagraj Crossing", "district": "Prayagraj", "lat": 26.5938, "lng": 83.7732, "accidents": 200, "fatalities": 53, "majorCause": "Lane Cutting", "vehicleType": "Truck", "roadType": "National Highway", "riskLevel": "High", "safetyTip": "Signal early before changing lanes and check blind spots.", "yearly": {"2019": 35, "2020": 34, "2021": 26, "2022": 30, "2023": 33, "2024": 42}, "severity": "Major"}, {"id": "uttar-pradesh-h5", "location": "Varanasi Junction", "district": "Varanasi", "lat": 25.2207, "lng": 82.3061, "accidents": 261, "fatalities": 90, "majorCause": "Poor Road Visibility", "vehicleType": "Others", "roadType": "City Road", "riskLevel": "Critical", "safetyTip": "Slow down and use headlights on low beam in poor visibility zones.", "yearly": {"2019": 57, "2020": 46, "2021": 31, "2022": 46, "2023": 26, "2024": 60}, "severity": "Minor"}, {"id": "uttar-pradesh-h6", "location": "Meerut Flyover", "district": "Meerut", "lat": 27.2924, "lng": 81.9099, "accidents": 414, "fatalities": 91, "majorCause": "Vehicle Overloading", "vehicleType": "Bike", "roadType": "City Road", "riskLevel": "Critical", "safetyTip": "Avoid overloading \u2014 it destabilizes vehicles and increases braking distance.", "yearly": {"2019": 66, "2020": 54, "2021": 72, "2022": 42, "2023": 81, "2024": 93}, "severity": "Minor"}, {"id": "uttar-pradesh-h7", "location": "Noida Ring Road", "district": "Noida", "lat": 27.1408, "lng": 78.4424, "accidents": 268, "fatalities": 50, "majorCause": "Pothole Damage", "vehicleType": "Bus", "roadType": "City Road", "riskLevel": "Critical", "safetyTip": "Watch for road damage warnings and keep both hands on the wheel.", "yearly": {"2019": 57, "2020": 53, "2021": 27, "2022": 43, "2023": 54, "2024": 58}, "severity": "Major"}, {"id": "uttar-pradesh-h8", "location": "Lucknow Crossing", "district": "Lucknow", "lat": 26.1469, "lng": 82.9865, "accidents": 182, "fatalities": 55, "majorCause": "Pothole Damage", "vehicleType": "Car", "roadType": "City Road", "riskLevel": "High", "safetyTip": "Watch for road damage warnings and keep both hands on the wheel.", "yearly": {"2019": 31, "2020": 25, "2021": 36, "2022": 35, "2023": 33, "2024": 32}, "severity": "Minor"}, {"id": "uttar-pradesh-h9", "location": "Lucknow Bridge", "district": "Lucknow", "lat": 27.3389, "lng": 77.9711, "accidents": 476, "fatalities": 138, "majorCause": "Fog & Low Visibility", "vehicleType": "Auto", "roadType": "City Road", "riskLevel": "Critical", "safetyTip": "Use fog lamps, keep extra following distance, and avoid sudden lane changes.", "yearly": {"2019": 103, "2020": 54, "2021": 70, "2022": 86, "2023": 70, "2024": 58}, "severity": "Minor"}, {"id": "uttar-pradesh-h10", "location": "Ghaziabad Highway Stretch", "district": "Ghaziabad", "lat": 27.4012, "lng": 82.8247, "accidents": 348, "fatalities": 76, "majorCause": "Poor Road Visibility", "vehicleType": "Bus", "roadType": "State Highway", "riskLevel": "Critical", "safetyTip": "Slow down and use headlights on low beam in poor visibility zones.", "yearly": {"2019": 69, "2020": 69, "2021": 75, "2022": 67, "2023": 69, "2024": 70}, "severity": "Minor"}, {"id": "uttar-pradesh-h11", "location": "Lucknow Chowk", "district": "Lucknow", "lat": 28.9087, "lng": 78.7386, "accidents": 290, "fatalities": 69, "majorCause": "Drunk Driving", "vehicleType": "Bus", "roadType": "City Road", "riskLevel": "Critical", "safetyTip": "Never drive under the influence. Use a designated driver or cab service.", "yearly": {"2019": 47, "2020": 49, "2021": 33, "2022": 56, "2023": 55, "2024": 49}, "severity": "Fatal"}, {"id": "uttar-pradesh-h12", "location": "Kanpur Nagar Bypass", "district": "Kanpur Nagar", "lat": 25.68, "lng": 82.057, "accidents": 464, "fatalities": 134, "majorCause": "Poor Road Visibility", "vehicleType": "Truck", "roadType": "National Highway", "riskLevel": "Critical", "safetyTip": "Slow down and use headlights on low beam in poor visibility zones.", "yearly": {"2019": 51, "2020": 70, "2021": 57, "2022": 105, "2023": 51, "2024": 56}, "severity": "Minor"}, {"id": "uttar-pradesh-h13", "location": "Lucknow Junction", "district": "Lucknow", "lat": 29.0805, "lng": 78.5458, "accidents": 311, "fatalities": 100, "majorCause": "Sharp Curve", "vehicleType": "Bike", "roadType": "Village Road", "riskLevel": "Critical", "safetyTip": "Reduce speed well before curves and avoid overtaking on bends.", "yearly": {"2019": 69, "2020": 50, "2021": 48, "2022": 61, "2023": 31, "2024": 38}, "severity": "Major"}, {"id": "uttar-pradesh-h14", "location": "Ghaziabad Chowk", "district": "Ghaziabad", "lat": 25.7365, "lng": 81.9479, "accidents": 351, "fatalities": 64, "majorCause": "Pedestrian Crossing", "vehicleType": "Bus", "roadType": "National Highway", "riskLevel": "Critical", "safetyTip": "Yield to pedestrians at crossings and reduce speed near markets and schools.", "yearly": {"2019": 57, "2020": 66, "2021": 59, "2022": 60, "2023": 56, "2024": 61}, "severity": "Minor"}, {"id": "uttar-pradesh-h15", "location": "Prayagraj Bus Stand Road", "district": "Prayagraj", "lat": 26.0583, "lng": 80.3629, "accidents": 205, "fatalities": 59, "majorCause": "Overspeeding", "vehicleType": "Others", "roadType": "City Road", "riskLevel": "High", "safetyTip": "Maintain speed limits, especially near junctions \u2014 braking distance doubles at high speed.", "yearly": {"2019": 32, "2020": 25, "2021": 45, "2022": 39, "2023": 28, "2024": 47}, "severity": "Minor"}, {"id": "uttar-pradesh-h16", "location": "Kanpur Nagar Flyover", "district": "Kanpur Nagar", "lat": 28.7131, "lng": 77.4117, "accidents": 477, "fatalities": 107, "majorCause": "Overspeeding", "vehicleType": "Auto", "roadType": "Village Road", "riskLevel": "Critical", "safetyTip": "Maintain speed limits, especially near junctions \u2014 braking distance doubles at high speed.", "yearly": {"2019": 75, "2020": 71, "2021": 60, "2022": 92, "2023": 90, "2024": 109}, "severity": "Major"}], "analytics": {"vehicleType": {"Car": 11164, "Bike": 15321, "Bus": 3851, "Truck": 7565, "Auto": 4983, "Others": 3261}, "severity": {"Minor": 22986, "Major": 14366, "Fatal": 10535}, "yearly": [{"year": 2019, "accidents": 8933, "fatalities": 3390}, {"year": 2020, "accidents": 7308, "fatalities": 2962}, {"year": 2021, "accidents": 7877, "fatalities": 2304}, {"year": 2022, "accidents": 9753, "fatalities": 3398}, {"year": 2023, "accidents": 8275, "fatalities": 2079}, {"year": 2024, "accidents": 8241, "fatalities": 3281}], "monthly": [{"month": "Jan", "accidents": 3155}, {"month": "Feb", "accidents": 3106}, {"month": "Mar", "accidents": 3549}, {"month": "Apr", "accidents": 3879}, {"month": "May", "accidents": 3888}, {"month": "Jun", "accidents": 4031}, {"month": "Jul", "accidents": 3645}, {"month": "Aug", "accidents": 3521}, {"month": "Sep", "accidents": 4049}, {"month": "Oct", "accidents": 4342}, {"month": "Nov", "accidents": 4398}, {"month": "Dec", "accidents": 4544}], "topDistricts": [{"district": "Lucknow", "accidents": 11331}, {"district": "Kanpur Nagar", "accidents": 7528}, {"district": "Agra", "accidents": 7479}, {"district": "Varanasi", "accidents": 6048}, {"district": "Ghaziabad", "accidents": 5592}, {"district": "Prayagraj", "accidents": 4860}, {"district": "Meerut", "accidents": 3726}, {"district": "Noida", "accidents": 2680}], "roadType": {"National Highway": 17438, "State Highway": 11776, "City Road": 14099, "Village Road": 4615}}}